airflow/providers/infisical/__init__.py
airflow/providers/infisical/_internal_client/__init__.py
airflow/providers/infisical/_internal_client/infisical_client.py
airflow/providers/infisical/secrets/__init__.py
airflow/providers/infisical/secrets/infisical.py
airflow_provider_infisical-0.0.1.dist-info/LICENSE
airflow_provider_infisical-0.0.1.dist-info/METADATA
airflow_provider_infisical-0.0.1.dist-info/WHEEL
airflow_provider_infisical-0.0.1.dist-info/entry_points.txt
airflow_provider_infisical-0.0.1.dist-info/top_level.txt
airflow_provider_infisical-0.0.1.dist-info/RECORD
