Metadata-Version: 2.1
Name: airflow-provider-infisical
Version: 0.0.1
Summary: An Airflow provider to connect to Infisical
Author-email: Daniel Hougaard <daniel@infisical.com>
License: Apache License 2.0
Project-URL: Source, https://github.com/infisical/airflow-provider-infisical
Keywords: airflow,infisical,infisical-provider,secrets,secrets-management
Classifier: Framework :: Apache Airflow
Classifier: Framework :: Apache Airflow :: Provider
Requires-Python: >=3.8
License-File: LICENSE
Requires-Dist: apache-airflow>=2.9.0
Requires-Dist: infisicalsdk>=1.0.6
